langchain_google_bigtable/__init__.py
langchain_google_bigtable/async_key_value_store.py
langchain_google_bigtable/async_vector_store.py
langchain_google_bigtable/chat_message_history.py
langchain_google_bigtable/common.py
langchain_google_bigtable/engine.py
langchain_google_bigtable/key_value_store.py
langchain_google_bigtable/loader.py
langchain_google_bigtable/py.typed
langchain_google_bigtable/vector_store.py
langchain_google_bigtable/version.py
langchain_google_bigtable-0.8.0.dist-info/licenses/LICENSE
langchain_google_bigtable-0.8.0.dist-info/METADATA
langchain_google_bigtable-0.8.0.dist-info/WHEEL
langchain_google_bigtable-0.8.0.dist-info/top_level.txt
langchain_google_bigtable-0.8.0.dist-info/RECORD
