Metadata-Version: 2.4
Name: langchain-google-bigtable
Version: 0.8.0
Summary: LangChain integrations for Google Cloud Bigtable
Author-email: Google LLC <googleapis-packages@google.com>
License: 
Project-URL: Homepage, https://github.com/googleapis/langchain-google-bigtable-python
Project-URL: Repository, https://github.com/googleapis/langchain-google-bigtable-python.git
Project-URL: Bug Tracker, https://github.com/googleapis/langchain-google-bigtable-python/issues
Project-URL: Changelog, https://github.com/googleapis/langchain-google-bigtable-python/blob/main/CHANGELOG.md
Classifier: Intended Audience :: Developers
Classifier: License :: OSI Approved :: Apache Software License
Classifier: Programming Language :: Python
Classifier: Programming Language :: Python :: 3
Classifier: Programming Language :: Python :: 3.9
Classifier: Programming Language :: Python :: 3.10
Classifier: Programming Language :: Python :: 3.11
Classifier: Programming Language :: Python :: 3.12
Requires-Python: >=3.9
License-File: LICENSE
Requires-Dist: langchain-core<1.0.0,>=0.1.1
Requires-Dist: google-cloud-bigtable<3.0.0,>=2.22.0
Requires-Dist: deprecated<2.0.0,>=1.2.14
Requires-Dist: typing-extensions>=4.12.0
Requires-Dist: numpy<3.0.0,>=1.24.4; python_version >= "3.11"
Requires-Dist: numpy<=2.2.6,>=1.24.4; python_version == "3.10"
Requires-Dist: numpy<=2.0.2,>=1.24.4; python_version <= "3.9"
Provides-Extra: test
Requires-Dist: black[jupyter]==25.1.0; extra == "test"
Requires-Dist: isort==6.0.1; extra == "test"
Requires-Dist: mypy==1.17.0; extra == "test"
Requires-Dist: pytest-asyncio==1.1.0; extra == "test"
Requires-Dist: pytest==8.4.1; extra == "test"
Requires-Dist: pytest-cov==6.2.1; extra == "test"
Dynamic: license-file
